{"users": [
  {
    "id": "5e28946a28ec7bf7c308b153",
    "balance": 1618,
    "age": 52,
    "name": {
      "first": "Allison",
      "last": "Bradshaw"
    },
    "company": "XINWARE",
    "email": "allison.bradshaw@xinware.info",
    "phone": "+1 (945) 448-3575",
    "address": "763 Seaview Court, Allensworth, Washington, 6529"
  },
  {
    "id": "5e28946aab83d4ce1c114d5a",
    "balance": 2770,
    "age": 52,
    "name": {
      "first": "Sheila",
      "last": "Flynn"
    },
    "company": "FLUMBO",
    "email": "sheila.flynn@flumbo.ca",
    "phone": "+1 (831) 499-3347",
    "address": "567 Nova Court, Lewis, Rhode Island, 8274"
  },
  {
    "id": "5e28946abc37c0aee4c00bc8",
    "balance": 3038,
    "age": 54,
    "name": {
      "first": "Lauren",
      "last": "Logan"
    },
    "company": "ECLIPTO",
    "email": "lauren.logan@eclipto.tv",
    "phone": "+1 (805) 437-2564",
    "address": "805 Dover Street, Grandview, Utah, 341"
  },
  {
    "id": "5e28946a04216da2108a4b04",
    "balance": 1799,
    "age": 62,
    "name": {
      "first": "Morrison",
      "last": "Herring"
    },
    "company": "IPLAX",
    "email": "morrison.herring@iplax.com",
    "phone": "+1 (982) 464-2164",
    "address": "219 Woodbine Street, Moquino, Delaware, 874"
  },
  {
    "id": "5e28946af31d4d241b37d673",
    "balance": 3237,
    "age": 41,
    "name": {
      "first": "Avila",
      "last": "Houston"
    },
    "company": "CONFERIA",
    "email": "avila.houston@conferia.name",
    "phone": "+1 (816) 592-2543",
    "address": "889 Guernsey Street, Leming, New York, 8842"
  },
  {
    "id": "5e28946a99d9c5edb4a87067",
    "balance": 2601,
    "age": 52,
    "name": {
      "first": "Howard",
      "last": "Lindsey"
    },
    "company": "SYBIXTEX",
    "email": "howard.lindsey@sybixtex.co.uk",
    "phone": "+1 (985) 485-3460",
    "address": "260 Lloyd Court, Wattsville, Kansas, 9332"
  },
  {
    "id": "5e28946a680050057bca8528",
    "balance": 1432,
    "age": 61,
    "name": {
      "first": "Washington",
      "last": "Cote"
    },
    "company": "EXIAND",
    "email": "washington.cote@exiand.io",
    "phone": "+1 (855) 517-3575",
    "address": "139 Himrod Street, Bentley, Guam, 9224"
  },
  {
    "id": "5e28946ad1c2632e29096823",
    "balance": 1522,
    "age": 23,
    "name": {
      "first": "Ellen",
      "last": "Yang"
    },
    "company": "DYNO",
    "email": "ellen.yang@dyno.biz",
    "phone": "+1 (847) 554-2598",
    "address": "772 Commerce Street, Topaz, Wyoming, 9622"
  },
  {
    "id": "5e28946a7a6f6de7929a768e",
    "balance": 3326,
    "age": 41,
    "name": {
      "first": "Valarie",
      "last": "Moody"
    },
    "company": "JASPER",
    "email": "valarie.moody@jasper.net",
    "phone": "+1 (815) 599-2954",
    "address": "692 Whitney Avenue, Lacomb, South Carolina, 4363"
  },
  {
    "id": "5e28946a12155dc00170c320",
    "balance": 2477,
    "age": 20,
    "name": {
      "first": "Stephanie",
      "last": "Keller"
    },
    "company": "AQUOAVO",
    "email": "stephanie.keller@aquoavo.me",
    "phone": "+1 (899) 538-3397",
    "address": "562 Hunterfly Place, Waterloo, Virginia, 8452"
  },
  {
    "id": "5e28946a9a18e556ab62ed68",
    "balance": 2075,
    "age": 52,
    "name": {
      "first": "Ramirez",
      "last": "Rich"
    },
    "company": "QUAILCOM",
    "email": "ramirez.rich@quailcom.org",
    "phone": "+1 (981) 518-3124",
    "address": "977 Willow Street, Richville, Nebraska, 8025"
  },
  {
    "id": "5e28946a0ddfb82b2227a9c1",
    "balance": 2052,
    "age": 47,
    "name": {
      "first": "Karla",
      "last": "Camacho"
    },
    "company": "XIIX",
    "email": "karla.camacho@xiix.biz",
    "phone": "+1 (925) 585-2450",
    "address": "976 Love Lane, Morgandale, Nevada, 428"
  },
  {
    "id": "5e28946a5b4304a42fa7f37d",
    "balance": 1236,
    "age": 38,
    "name": {
      "first": "Aurelia",
      "last": "Dean"
    },
    "company": "NAXDIS",
    "email": "aurelia.dean@naxdis.info",
    "phone": "+1 (808) 573-2535",
    "address": "896 Ford Street, Stevens, Tennessee, 6042"
  }
]}